Workbook

Sheet 説明
A1: 制作サンプル：経営診断エージェント 入力受け皿（標準科目）への当てはめ
A3: 対象 | B3: アルファ製菓株式会社 第73期（2025年4月1日〜2026年3月31日）単体財務諸表
A4: 出典 | B4: 有価証券報告書（モデル。数値は一定の係数で変換）
A5: 単位 | B5: 千円（原資料どおり。千円未満切捨てのため、合計と内訳に±2千円程度の端数差が生じうる）
A6: 用途 | B6: システムの原理を作るための制作サンプル。外部に示す際は業種名を変え、数値を一定倍率で変換して匿名化する
A8: シート構成
A9: 標準科目対応 | B9: 原資料の科目を標準科目に当てはめ、前期・当期の数値と出典頁、対応状態を記録
A10: 検算 | B10: 読み取り値の整合性を自動で確かめる。不一致があれば論争に進まず止める
A11: 欠落と扱い | B11: 標準科目のうち原資料で埋まらないものと、システムの扱い（該当なし・埋没・未確認）
A13: 凡例
A14: 青字 | B14: 原資料から読み取った数値（入力）
A15: 黒字 | B15: 計算式
A16: 対応状態 | B16: 対応／名称のみ相違／統合表示／他表から分割可／上場企業特有／合計（検算用）
A17: 方針 | B17: 株式の時価評価（その他有価証券評価差額金・繰延税金負債）は原資料どおり保持し、加工しない。『本業の姿』は別の補助計算で示す（次工程）

Sheet 標準科目対応
A1: 表 | B1: 区分 | C1: 標準科目 | D1: 原資料の科目 | E1: 前期（2025/3） | F1: 当期（2026/3） | G1: 対応状態 | H1: 出典頁 | I1: 備考
A2: BS | B2: 流動資産 | C2: 現金預金 | D2: 現金及び預金 | E2: 3115370 | F2: 1775593 | G2: 名称のみ相違 | H2: p.91
A3: BS | B3: 流動資産 | C3: 受取手形 | D3: 受取手形 | E3: 3358 | F3: 1442 | G3: 対応 | H3: p.91
A4: BS | B4: 流動資産 | C4: 売掛金 | D4: 売掛金 | E4: 6052058 | F4: 6043850 | G4: 対応 | H4: p.91
A5: BS | B5: 流動資産 | C5: 製品・商品 | D5: 商品及び製品 | E5: 544561 | F5: 1080987 | G5: 他表から分割可 | H5: p.91 | I5: 製造原価明細書の売上原価調整表で期末製品725,962／期末商品355,025に分割可
A6: BS | B6: 流動資産 | C6: 仕掛品 | D6: 仕掛品 | E6: 159540 | F6: 182953 | G6: 対応 | H6: p.91
A7: BS | B7: 流動資産 | C7: 原材料 | D7: 原材料及び貯蔵品 | E7: 1234522 | F7: 1897578 | G7: 統合表示 | H7: p.91 | I7: 原材料と貯蔵品は分割不可
A8: BS | B8: 流動資産 | C8: 前払費用 | D8: 前払費用 | E8: 111225 | F8: 118336 | G8: 対応 | H8: p.91
A9: BS | B9: 流動資産 | C9: その他流動資産 | D9: その他 | E9: 73665 | F9: 212878 | G9: 統合表示 | H9: p.91 | I9: 未収入金・仮払金・未収消費税等が埋没（連結注記では未収消費税等が増加と説明）
A10: BS | B10: 流動資産 | C10: 貸倒引当金（流動） | D10: 貸倒引当金 | E10: -36961 | F10: 0 | G10: 対応 | H10: p.91 | I10: 当期は「－」
A11: BS | B11: 流動資産 | C11: 流動資産合計 | D11: 流動資産合計 | E11: 11257340 | F11: 11313622 | G11: 合計（検算用） | H11: p.91
A12: BS | B12: 有形固定資産 | C12: 建物 | D12: 建物 | E12: 7341480 | F12: 7861541 | G12: 対応 | H12: p.91 | I12: 純額（減価償却累計額控除後）表示
A13: BS | B13: 有形固定資産 | C13: 構築物 | D13: 構築物 | E13: 466347 | F13: 480485 | G13: 対応 | H13: p.91
A14: BS | B14: 有形固定資産 | C14: 機械装置 | D14: 機械及び装置 | E14: 5609616 | F14: 6289858 | G14: 名称のみ相違 | H14: p.91
A15: BS | B15: 有形固定資産 | C15: 車両運搬具 | D15: 車両運搬具 | E15: 13380 | F15: 24011 | G15: 対応 | H15: p.91
A16: BS | B16: 有形固定資産 | C16: 工具器具備品 | D16: 工具、器具及び備品 | E16: 142891 | F16: 185104 | G16: 名称のみ相違 | H16: p.91
A17: BS | B17: 有形固定資産 | C17: 土地 | D17: 土地 | E17: 824922 | F17: 967832 | G17: 対応 | H17: p.91
A18: BS | B18: 有形固定資産 | C18: リース資産 | D18: リース資産 | E18: 59453 | F18: 64659 | G18: 対応 | H18: p.91
A19: BS | B19: 有形固定資産 | C19: 建設仮勘定 | D19: 建設仮勘定 | E19: 817424 | F19: 247992 | G19: 対応 | H19: p.91
A20: BS | B20: 有形固定資産 | C20: 有形固定資産合計 | D20: 有形固定資産合計 | E20: 15275516 | F20: 16121486 | G20: 合計（検算用） | H20: p.91
A21: BS | B21: 無形固定資産 | C21: ソフトウェア | D21: ソフトウエア | E21: 46581 | F21: 29099 | G21: 名称のみ相違 | H21: p.91
A22: BS | B22: 無形固定資産 | C22: その他無形 | D22: その他 | E22: 10841 | F22: 22148 | G22: 統合表示 | H22: p.91
A23: BS | B23: 無形固定資産 | C23: 無形固定資産合計 | D23: 無形固定資産合計 | E23: 57423 | F23: 51248 | G23: 合計（検算用） | H23: p.91
A24: BS | B24: 投資その他 | C24: 投資有価証券 | D24: 投資有価証券 | E24: 65507110 | F24: 66405773 | G24: 上場企業特有 | H24: p.91 | I24: 時価評価。うち大半が旺旺集団株式（貸借対照表計上額58,936,200：p.58）
A25: BS | B25: 投資その他 | C25: 関係会社株式 | D25: 関係会社株式 | E25: 183623 | F25: 183623 | G25: 対応 | H25: p.91
A26: BS | B26: 投資その他 | C26: 出資金 | D26: 出資金 | E26: 1233 | F26: 1233 | G26: 対応 | H26: p.91
A27: BS | B27: 投資その他 | C27: 長期貸付金 | D27: 従業員に対する長期貸付金 | E27: 2903 | F27: 2091 | G27: 名称のみ相違 | H27: p.91 | I27: 役員・代表者への貸付は該当なし
A28: BS | B28: 投資その他 | C28: 長期前払費用 | D28: 長期前払費用 | E28: 42401 | F28: 28939 | G28: 対応 | H28: p.91
A29: BS | B29: 投資その他 | C29: 差入保証金 | D29: 差入保証金 | E29: 75626 | F29: 57054 | G29: 対応 | H29: p.91
A30: BS | B30: 投資その他 | C30: その他投資 | D30: その他 | E30: 150078 | F30: 198610 | G30: 統合表示 | H30: p.91 | I30: 保険積立金・ゴルフ会員権等が埋没の可能性
A31: BS | B31: 投資その他 | C31: 貸倒引当金（固定） | D31: 貸倒引当金 | E31: -33661 | F31: -73209 | G31: 対応 | H31: p.91
A32: BS | B32: 投資その他 | C32: 投資その他の資産合計 | D32: 投資その他の資産合計 | E32: 65929314 | F32: 66804115 | G32: 合計（検算用） | H32: p.91
A33: BS | B33: 固定資産 | C33: 固定資産合計 | D33: 固定資産合計 | E33: 81262253 | F33: 82976849 | G33: 合計（検算用） | H33: p.91
A34: BS | B34: 資産 | C34: 資産合計 | D34: 資産合計 | E34: 92519592 | F34: 94290472 | G34: 合計（検算用） | H34: p.91
A35: BS | B35: 流動負債 | C35: 買掛金 | D35: 買掛金 | E35: 1183426 | F35: 1409473 | G35: 対応 | H35: p.92
A36: BS | B36: 流動負債 | C36: 1年内返済長期借入金 | D36: １年内返済予定の長期借入金 | E36: 412824 | F36: 4532 | G36: 対応 | H36: p.92
A37: BS | B37: 流動負債 | C37: 1年内償還社債 | D37: １年内償還予定の社債 | E37: 0 | F37: 103000 | G37: 対応 | H37: p.92 | I37: 中小企業の私募債と同型
A38: BS | B38: 流動負債 | C38: リース債務（流動） | D38: リース債務 | E38: 18277 | F38: 21487 | G38: 対応 | H38: p.92
A39: BS | B39: 流動負債 | C39: 未払金 | D39: 未払金 | E39: 1093664 | F39: 878773 | G39: 対応 | H39: p.92
A40: BS | B40: 流動負債 | C40: 未払費用 | D40: 未払費用 | E40: 592292 | F40: 572793 | G40: 対応 | H40: p.92
A41: BS | B41: 流動負債 | C41: 返金負債 | D41: 返金負債 | E41: 722155 | F41: 672453 | G41: 上場企業特有 | H41: p.92 | I41: リベート等の見積り。中小企業では未払金・売上値引等で処理されることが多い
A42: BS | B42: 流動負債 | C42: 未払法人税等 | D42: 未払法人税等 | E42: 138907 | F42: 432471 | G42: 対応 | H42: p.92
A43: BS | B43: 流動負債 | C43: 未払消費税 | D43: 未払消費税等 | E43: 54905 | F43: 0 | G43: 名称のみ相違 | H43: p.92
A44: BS | B44: 流動負債 | C44: 預り金 | D44: 預り金 | E44: 24736 | F44: 27816 | G44: 対応 | H44: p.92
A45: BS | B45: 流動負債 | C45: 前受収益 | D45: 前受収益 | E45: 300 | F45: 345 | G45: 対応 | H45: p.92
A46: BS | B46: 流動負債 | C46: 賞与引当金 | D46: 賞与引当金 | E46: 523839 | F46: 547559 | G46: 対応 | H46: p.92
A47: BS | B47: 流動負債 | C47: その他流動負債 | D47: その他 | E47: 3580 | F47: 3301 | G47: 統合表示 | H47: p.92
A48: BS | B48: 流動負債 | C48: 流動負債合計 | D48: 流動負債合計 | E48: 4768912 | F48: 4674008 | G48: 合計（検算用） | H48: p.92
A49: BS | B49: 固定負債 | C49: 社債 | D49: 社債 | E49: 206000 | F49: 103000 | G49: 対応 | H49: p.92
A50: BS | B50: 固定負債 | C50: 長期借入金 | D50: 長期借入金 | E50: 4532 | F50: 0 | G50: 対応 | H50: p.92
A51: BS | B51: 固定負債 | C51: 長期預り保証金 | D51: 長期預り保証金 | E51: 105187 | F51: 98431 | G51: 対応 | H51: p.92
A52: BS | B52: 固定負債 | C52: リース債務（固定） | D52: リース債務 | E52: 50234 | F52: 51853 | G52: 対応 | H52: p.92
A53: BS | B53: 固定負債 | C53: 退職給付引当金 | D53: 退職給付引当金 | E53: 1277133 | F53: 1306696 | G53: 対応 | H53: p.92
A54: BS | B54: 固定負債 | C54: 役員株式給付引当金 | D54: 役員株式給付引当金 | E54: 51909 | F54: 67052 | G54: 上場企業特有 | H54: p.92
A55: BS | B55: 固定負債 | C55: 繰延税金負債 | D55: 繰延税金負債 | E55: 17086924 | F55: 17322399 | G55: 上場企業特有 | H55: p.92 | I55: 大半は株式含み益に係るもの。中小企業は税効果会計を通常適用しない
A56: BS | B56: 固定負債 | C56: その他固定負債 | D56: その他 | E56: 98517 | F56: 113170 | G56: 統合表示 | H56: p.92
A57: BS | B57: 固定負債 | C57: 固定負債合計 | D57: 固定負債合計 | E57: 18880439 | F57: 19062604 | G57: 合計（検算用） | H57: p.92
A58: BS | B58: 負債 | C58: 負債合計 | D58: 負債合計 | E58: 23649351 | F58: 23736614 | G58: 合計（検算用） | H58: p.92
A59: BS | B59: 純資産 | C59: 資本金 | D59: 資本金 | E59: 1683793 | F59: 1683793 | G59: 対応 | H59: p.92
A60: BS | B60: 純資産 | C60: 資本準備金 | D60: 資本準備金 | E60: 1915028 | F60: 1915028 | G60: 対応 | H60: p.92
A61: BS | B61: 純資産 | C61: 利益準備金 | D61: 利益準備金 | E61: 104480 | F61: 104480 | G61: 対応 | H61: p.92
A62: BS | B62: 純資産 | C62: 別途積立金 | D62: 別途積立金 | E62: 22847460 | F62: 25370960 | G62: 対応 | H62: p.92
A63: BS | B63: 純資産 | C63: 繰越利益剰余金 | D63: 繰越利益剰余金 | E63: 2853922 | F63: 1876911 | G63: 対応 | H63: p.92
A64: BS | B64: 純資産 | C64: 利益剰余金合計 | D64: 利益剰余金合計 | E64: 25805863 | F64: 27352351 | G64: 合計（検算用） | H64: p.92
A65: BS | B65: 純資産 | C65: 自己株式 | D65: 自己株式 | E65: -3232515 | F65: -3677072 | G65: 上場企業特有 | H65: p.92
A66: BS | B66: 純資産 | C66: 株主資本合計 | D66: 株主資本合計 | E66: 26172168 | F66: 27274099 | G66: 合計（検算用） | H66: p.92
A67: BS | B67: 純資産 | C67: 評価差額金 | D67: その他有価証券評価差額金 | E67: 42698072 | F67: 43279758 | G67: 上場企業特有 | H67: p.92 | I67: 時価評価を原資料どおり保持（方針）
A68: BS | B68: 純資産 | C68: 純資産合計 | D68: 純資産合計 | E68: 68870241 | F68: 70553858 | G68: 合計（検算用） | H68: p.92
A69: BS | B69: 負債純資産 | C69: 負債純資産合計 | D69: 負債純資産合計 | E69: 92519592 | F69: 94290472 | G69: 合計（検算用） | H69: p.92
A70: PL | B70: 売上 | C70: 売上高 | D70: 売上高 | E70: 24298452 | F70: 28148648 | G70: 対応 | H70: p.93
A71: PL | B71: 売上原価 | C71: 売上原価 | D71: 売上原価 | E71: 18449243 | F71: 22045670 | G71: 対応 | H71: p.93 | I71: 内訳は製造原価明細書の調整表
A72: PL | B72: 利益 | C72: 売上総利益 | D72: 売上総利益 | E72: 5849209 | F72: 6102978 | G72: 合計（検算用） | H72: p.93
A73: PL | B73: 販管費 | C73: 販売費 | D73: 販売費 | E73: 3681885 | F73: 3811305 | G73: 対応 | H73: p.93 | I73: 細目は注記（p.98以降）で要確認
A74: PL | B74: 販管費 | C74: 一般管理費 | D74: 一般管理費 | E74: 1520867 | F74: 1643033 | G74: 対応 | H74: p.93
A75: PL | B75: 販管費 | C75: 販管費合計 | D75: 販売費及び一般管理費合計 | E75: 5202754 | F75: 5454338 | G75: 合計（検算用） | H75: p.93
A76: PL | B76: 利益 | C76: 営業利益 | D76: 営業利益 | E76: 646455 | F76: 648638 | G76: 合計（検算用） | H76: p.93
A77: PL | B77: 営業外収益 | C77: 受取利息 | D77: 受取利息 | E77: 1815 | F77: 3164 | G77: 対応 | H77: p.93
A78: PL | B78: 営業外収益 | C78: 受取配当金 | D78: 受取配当金 | E78: 2954604 | F78: 1908653 | G78: 対応 | H78: p.93 | I78: 大半が旺旺集団からの配当（連結ベースで当期1,843百万円：p.24）
A79: PL | B79: 営業外収益 | C79: 雑収入 | D79: その他 | E79: 311259 | F79: 145589 | G79: 名称のみ相違 | H79: p.93
A80: PL | B80: 営業外収益 | C80: 営業外収益合計 | D80: 営業外収益合計 | E80: 3267679 | F80: 2057407 | G80: 合計（検算用） | H80: p.93
A81: PL | B81: 営業外費用 | C81: 支払利息 | D81: 支払利息 | E81: 5851 | F81: 3353 | G81: 対応 | H81: p.93
A82: PL | B82: 営業外費用 | C82: 貸倒引当金繰入額 | D82: 貸倒引当金繰入額 | E82: 0 | F82: 2586 | G82: 対応 | H82: p.93
A83: PL | B83: 営業外費用 | C83: 休止固定資産減価償却費 | D83: 休止固定資産減価償却費 | E83: 4935 | F83: 9716 | G83: 対応 | H83: p.93 | I83: 標準科目に追加候補
A84: PL | B84: 営業外費用 | C84: 雑損失 | D84: その他 | E84: 1805 | F84: 2026 | G84: 名称のみ相違 | H84: p.93
A85: PL | B85: 営業外費用 | C85: 営業外費用合計 | D85: 営業外費用合計 | E85: 12592 | F85: 17682 | G85: 合計（検算用） | H85: p.93
A86: PL | B86: 利益 | C86: 経常利益 | D86: 経常利益 | E86: 3901542 | F86: 2688365 | G86: 合計（検算用） | H86: p.93
A87: PL | B87: 特別利益 | C87: 固定資産売却益 | D87: 固定資産売却益 | E87: 226 | F87: 627 | G87: 対応 | H87: p.93
A88: PL | B88: 特別利益 | C88: 投資有価証券売却益 | D88: 投資有価証券売却益 | E88: 0 | F88: 51260 | G88: 対応 | H88: p.93
A89: PL | B89: 特別利益 | C89: 特別利益合計 | D89: 特別利益合計 | E89: 226 | F89: 51888 | G89: 合計（検算用） | H89: p.93
A90: PL | B90: 特別損失 | C90: 固定資産除却損 | D90: 固定資産除却損 | E90: 7707 | F90: 28865 | G90: 対応 | H90: p.93
A91: PL | B91: 特別損失 | C91: 固定資産売却損 | D91: 固定資産売却損 | E91: 0 | F91: 5886 | G91: 対応 | H91: p.93
A92: PL | B92: 特別損失 | C92: 投資有価証券評価損 | D92: 投資有価証券評価損 | E92: 9305 | F92: 1957 | G92: 対応 | H92: p.93
A93: PL | B93: 特別損失 | C93: リース解約損 | D93: リース解約損 | E93: 756 | F93: 1408 | G93: 対応 | H93: p.93
A94: PL | B94: 特別損失 | C94: 解決金 | D94: 解決金 | E94: 13870 | F94: 0 | G94: 対応 | H94: p.93
A95: PL | B95: 特別損失 | C95: 特別損失合計 | D95: 特別損失合計 | E95: 31641 | F95: 38118 | G95: 合計（検算用） | H95: p.93
... A97: PL | B97: 税金 | C97: 法人税、住民税及び事業税 | D97: 法人税、住民税及び事業税 | E97: 825556 | F97: 848674 | G97: 対応 | H97: p.93
A98: PL | B98: 税金 | C98: 法人税等調整額 | D98: 法人税等調整額 | E98: 194429 | F98: -15783 | G98: 上場企業特有 | H98: p.93 | I98: 税効果会計
A99: PL | B99: 税金 | C99: 法人税等合計 | D99: 法人税等合計 | E99: 1019985 | F99: 832890 | G99: 合計（検算用） | H99: p.93
A100: PL | B100: 利益 | C100: 当期純利益 | D100: 当期純利益 | E100: 2850142 | F100: 1869244 | G100: 合計（検算用） | H100: p.93
A101: 製造原価 | B101: 製造費用 | C101: 材料費 | D101: 材料費 | E101: 9855888 | F101: 10453980 | G101: 対応 | H101: p.94 | I101: 原料米・副材料・包装資材の内訳は不明
...

Sheet 検算
A1: 許容差の考え方 | B1: 原資料は各科目・各合計を千円未満切捨てで表示するため、内訳n件の合計と報告合計は最大でn千円程度ずれうる。許容差＝内訳件数（最低2）とする
A3: 区分 | B3: 検算項目 | C3: 計算値（前期） | D3: 報告値（前期） | E3: 差（前期） | F3: 判定（前期） | G3: 計算値（当期） | H3: 報告値（当期） | I3: 差（当期） | J3: 判定（当期） | K3: 許容差
A4: BS内訳 | B4: 流動資産合計 | C4: =標準科目対応!E2+標準科目対応!E3+標準科目対応!E4+標準科目対応!E5+標準科目対応!E6+標準科目対応!E7+標準科目対応!E8+標準科目対応!E9+標準科目対応!E10 | D4: =標準科目対応!E11 | E4: =C4-D4 | F4: =IF(ABS(E4)<=$K$4,"一致","不一致") | G4: =標準科目対応!F2+標準科目対応!F3+標準科目対応!F4+標準科目対応!F5+標準科目対応!F6+標準科目対応!F7+標準科目対応!F8+標準科目対応!F9+標準科目対応!F10 | H4: =標準科目対応!F11 | I4: =G4-H4 | J4: =IF(ABS(I4)<=$K$4,"一致","不一致") | K4: 9
A5: BS内訳 | B5: 有形固定資産合計 | C5: =標準科目対応!E12+標準科目対応!E13+標準科目対応!E14+標準科目対応!E15+標準科目対応!E16+標準科目対応!E17+標準科目対応!E18+標準科目対応!E19 | D5: =標準科目対応!E20 | E5: =C5-D5 | F5: =IF(ABS(E5)<=$K$5,"一致","不一致") | G5: =標準科目対応!F12+標準科目対応!F13+標準科目対応!F14+標準科目対応!F15+標準科目対応!F16+標準科目対応!F17+標準科目対応!F18+標準科目対応!F19 | H5: =標準科目対応!F20 | I5: =G5-H5 | J5: =IF(ABS(I5)<=$K$5,"一致","不一致") | K5: 8
A6: BS内訳 | B6: 無形固定資産合計 | C6: =標準科目対応!E21+標準科目対応!E22 | D6: =標準科目対応!E23 | E6: =C6-D6 | F6: =IF(ABS(E6)<=$K$6,"一致","不一致") | G6: =標準科目対応!F21+標準科目対応!F22 | H6: =標準科目対応!F23 | I6: =G6-H6 | J6: =IF(ABS(I6)<=$K$6,"一致","不一致") | K6: 2
A7: BS内訳 | B7: 投資その他の資産合計 | C7: =標準科目対応!E24+標準科目対応!E25+標準科目対応!E26+標準科目対応!E27+標準科目対応!E28+標準科目対応!E29+標準科目対応!E30+標準科目対応!E31 | D7: =標準科目対応!E32 | E7: =C7-D7 | F7: =IF(ABS(E7)<=$K$7,"一致","不一致") | G7: =標準科目対応!F24+標準科目対応!F25+標準科目対応!F26+標準科目対応!F27+標準科目対応!F28+標準科目対応!F29+標準科目対応!F30+標準科目対応!F31 | H7: =標準科目対応!F32 | I7: =G7-H7 | J7: =IF(ABS(I7)<=$K$7,"一致","不一致") | K7: 8
A8: BS内訳 | B8: 固定資産合計 | C8: =標準科目対応!E20+標準科目対応!E23+標準科目対応!E32 | D8: =標準科目対応!E33 | E8: =C8-D8 | F8: =IF(ABS(E8)<=$K$8,"一致","不一致") | G8: =標準科目対応!F20+標準科目対応!F23+標準科目対応!F32 | H8: =標準科目対応!F33 | I8: =G8-H8 | J8: =IF(ABS(I8)<=$K$8,"一致","不一致") | K8: 3
A9: BS内訳 | B9: 資産合計 | C9: =標準科目対応!E11+標準科目対応!E33 | D9: =標準科目対応!E34 | E9: =C9-D9 | F9: =IF(ABS(E9)<=$K$9,"一致","不一致") | G9: =標準科目対応!F11+標準科目対応!F33 | H9: =標準科目対応!F34 | I9: =G9-H9 | J9: =IF(ABS(I9)<=$K$9,"一致","不一致") | K9: 2
A10: BS内訳 | B10: 流動負債合計 | C10: =標準科目対応!E35+標準科目対応!E36+標準科目対応!E37+標準科目対応!E38+標準科目対応!E39+標準科目対応!E40+標準科目対応!E41+標準科目対応!E42+標準科目対応!E43+標準科目対応!E44+標準科目対応!E45+標準科目対応!E46+標準科目対応!E47 | D10: =標準科目対応!E48 | E10: =C10-D10 | F10: =IF(ABS(E10)<=$K$10,"一致","不一致") | G10: =標準科目対応!F35+標準科目対応!F36+標準科目対応!F37+標準科目対応!F38+標準科目対応!F39+標準科目対応!F40+標準科目対応!F41+標準科目対応!F42+標準科目対応!F43+標準科目対応!F44+標準科目対応!F45+標準科目対応!F46+標準科目対応!F47 | H10: =標準科目対応!F48 | I10: =G10-H10 | J10: =IF(ABS(I10)<=$K$10,"一致","不一致") | K10: 13
A11: BS内訳 | B11: 固定負債合計 | C11: =標準科目対応!E49+標準科目対応!E50+標準科目対応!E51+標準科目対応!E52+標準科目対応!E53+標準科目対応!E54+標準科目対応!E55+標準科目対応!E56 | D11: =標準科目対応!E57 | E11: =C11-D11 | F11: =IF(ABS(E11)<=$K$11,"一致","不一致") | G11: =標準科目対応!F49+標準科目対応!F50+標準科目対応!F51+標準科目対応!F52+標準科目対応!F53+標準科目対応!F54+標準科目対応!F55+標準科目対応!F56 | H11: =標準科目対応!F57 | I11: =G11-H11 | J11: =IF(ABS(I11)<=$K$11,"一致","不一致") | K11: 8
A12: BS内訳 | B12: 負債合計 | C12: =標準科目対応!E48+標準科目対応!E57 | D12: =標準科目対応!E58 | E12: =C12-D12 | F12: =IF(ABS(E12)<=$K$12,"一致","不一致") | G12: =標準科目対応!F48+標準科目対応!F57 | H12: =標準科目対応!F58 | I12: =G12-H12 | J12: =IF(ABS(I12)<=$K$12,"一致","不一致") | K12: 2
A13: BS内訳 | B13: 利益剰余金合計 | C13: =標準科目対応!E61+標準科目対応!E62+標準科目対応!E63 | D13: =標準科目対応!E64 | E13: =C13-D13 | F13: =IF(ABS(E13)<=$K$13,"一致","不一致") | G13: =標準科目対応!F61+標準科目対応!F62+標準科目対応!F63 | H13: =標準科目対応!F64 | I13: =G13-H13 | J13: =IF(ABS(I13)<=$K$13,"一致","不一致") | K13: 3
A14: BS内訳 | B14: 株主資本合計 | C14: =標準科目対応!E59+標準科目対応!E60+標準科目対応!E64+標準科目対応!E65 | D14: =標準科目対応!E66 | E14: =C14-D14 | F14: =IF(ABS(E14)<=$K$14,"一致","不一致") | G14: =標準科目対応!F59+標準科目対応!F60+標準科目対応!F64+標準科目対応!F65 | H14: =標準科目対応!F66 | I14: =G14-H14 | J14: =IF(ABS(I14)<=$K$14,"一致","不一致") | K14: 4
A15: BS内訳 | B15: 純資産合計 | C15: =標準科目対応!E66+標準科目対応!E67 | D15: =標準科目対応!E68 | E15: =C15-D15 | F15: =IF(ABS(E15)<=$K$15,"一致","不一致") | G15: =標準科目対応!F66+標準科目対応!F67 | H15: =標準科目対応!F68 | I15: =G15-H15 | J15: =IF(ABS(I15)<=$K$15,"一致","不一致") | K15: 2
A16: 貸借一致 | B16: 負債合計＋純資産合計＝負債純資産合計 | C16: =標準科目対応!E58+標準科目対応!E68 | D16: =標準科目対応!E69 | E16: =C16-D16 | F16: =IF(ABS(E16)<=$K$16,"一致","不一致") | G16: =標準科目対応!F58+標準科目対応!F68 | H16: =標準科目対応!F69 | I16: =G16-H16 | J16: =IF(ABS(I16)<=$K$16,"一致","不一致") | K16: 2
A17: 貸借一致 | B17: 資産合計＝負債純資産合計 | C17: =標準科目対応!E34 | D17: =標準科目対応!E69 | E17: =C17-D17 | F17: =IF(ABS(E17)<=$K$17,"一致","不一致") | G17: =標準科目対応!F34 | H17: =標準科目対応!F69 | I17: =G17-H17 | J17: =IF(ABS(I17)<=$K$17,"一致","不一致") | K17: 2
A18: PL段階利益 | B18: 売上総利益 | C18: =標準科目対応!E70-標準科目対応!E71 | D18: =標準科目対応!E72 | E18: =C18-D18 | F18: =IF(ABS(E18)<=$K$18,"一致","不一致") | G18: =標準科目対応!F70-標準科目対応!F71 | H18: =標準科目対応!F72 | I18: =G18-H18 | J18: =IF(ABS(I18)<=$K$18,"一致","不一致") | K18: 2
A19: PL段階利益 | B19: 販管費合計 | C19: =標準科目対応!E73+標準科目対応!E74 | D19: =標準科目対応!E75 | E19: =C19-D19 | F19: =IF(ABS(E19)<=$K$19,"一致","不一致") | G19: =標準科目対応!F73+標準科目対応!F74 | H19: =標準科目対応!F75 | I19: =G19-H19 | J19: =IF(ABS(I19)<=$K$19,"一致","不一致") | K19: 2
A20: PL段階利益 | B20: 営業利益 | C20: =標準科目対応!E72-標準科目対応!E75 | D20: =標準科目対応!E76 | E20: =C20-D20 | F20: =IF(ABS(E20)<=$K$20,"一致","不一致") | G20: =標準科目対応!F72-標準科目対応!F75 | H20: =標準科目対応!F76 | I20: =G20-H20 | J20: =IF(ABS(I20)<=$K$20,"一致","不一致") | K20: 2
A21: PL段階利益 | B21: 営業外収益合計 | C21: =標準科目対応!E77+標準科目対応!E78+標準科目対応!E79 | D21: =標準科目対応!E80 | E21: =C21-D21 | F21: =IF(ABS(E21)<=$K$21,"一致","不一致") | G21: =標準科目対応!F77+標準科目対応!F78+標準科目対応!F79 | H21: =標準科目対応!F80 | I21: =G21-H21 | J21: =IF(ABS(I21)<=$K$21,"一致","不一致") | K21: 3
A22: PL段階利益 | B22: 営業外費用合計 | C22: =標準科目対応!E81+標準科目対応!E82+標準科目対応!E83+標準科目対応!E84 | D22: =標準科目対応!E85 | E22: =C22-D22 | F22: =IF(ABS(E22)<=$K$22,"一致","不一致") | G22: =標準科目対応!F81+標準科目対応!F82+標準科目対応!F83+標準科目対応!F84 | H22: =標準科目対応!F85 | I22: =G22-H22 | J22: =IF(ABS(I22)<=$K$22,"一致","不一致") | K22: 4
A23: PL段階利益 | B23: 経常利益 | C23: =標準科目対応!E76+標準科目対応!E80-標準科目対応!E85 | D23: =標準科目対応!E86 | E23: =C23-D23 | F23: =IF(ABS(E23)<=$K$23,"一致","不一致") | G23: =標準科目対応!F76+標準科目対応!F80-標準科目対応!F85 | H23: =標準科目対応!F86 | I23: =G23-H23 | J23: =IF(ABS(I23)<=$K$23,"一致","不一致") | K23: 3
A24: PL段階利益 | B24: 特別利益合計 | C24: =標準科目対応!E87+標準科目対応!E88 | D24: =標準科目対応!E89 | E24: =C24-D24 | F24: =IF(ABS(E24)<=$K$24,"一致","不一致") | G24: =標準科目対応!F87+標準科目対応!F88 | H24: =標準科目対応!F89 | I24: =G24-H24 | J24: =IF(ABS(I24)<=$K$24,"一致","不一致") | K24: 2
A25: PL段階利益 | B25: 特別損失合計 | C25: =標準科目対応!E90+標準科目対応!E91+標準科目対応!E92+標準科目対応!E93+標準科目対応!E94 | D25: =標準科目対応!E95 | E25: =C25-D25 | F25: =IF(ABS(E25)<=$K$25,"一致","不一致") | G25: =標準科目対応!F90+標準科目対応!F91+標準科目対応!F92+標準科目対応!F93+標準科目対応!F94 | H25: =標準科目対応!F95 | I25: =G25-H25 | J25: =IF(ABS(I25)<=$K$25,"一致","不一致") | K25: 5
A26: PL段階利益 | B26: 税引前当期純利益 | C26: =標準科目対応!E86+標準科目対応!E89-標準科目対応!E95 | D26: =標準科目対応!E96 | E26: =C26-D26 | F26: =IF(ABS(E26)<=$K$26,"一致","不一致") | G26: =標準科目対応!F86+標準科目対応!F89-標準科目対応!F95 | H26: =標準科目対応!F96 | I26: =G26-H26 | J26: =IF(ABS(I26)<=$K$26,"一致","不一致") | K26: 3
A27: PL段階利益 | B27: 法人税等合計 | C27: =標準科目対応!E97+標準科目対応!E98 | D27: =標準科目対応!E99 | E27: =C27-D27 | F27: =IF(ABS(E27)<=$K$27,"一致","不一致") | G27: =標準科目対応!F97+標準科目対応!F98 | H27: =標準科目対応!F99 | I27: =G27-H27 | J27: =IF(ABS(I27)<=$K$27,"一致","不一致") | K27: 2
A28: PL段階利益 | B28: 当期純利益 | C28: =標準科目対応!E96-標準科目対応!E99 | D28: =標準科目対応!E100 | E28: =C28-D28 | F28: =IF(ABS(E28)<=$K$28,"一致","不一致") | G28: =標準科目対応!F96-標準科目対応!F99 | H28: =標準科目対応!F100 | I28: =G28-H28 | J28: =IF(ABS(I28)<=$K$28,"一致","不一致") | K28: 2
A29: 製造原価の流れ | B29: 当期総製造費用 | C29: =標準科目対応!E101+標準科目対応!E102+標準科目対応!E103 | D29: =標準科目対応!E109 | E29: =C29-D29 | F29: =IF(ABS(E29)<=$K$29,"一致","不一致") | G29: =標準科目対応!F101+標準科目対応!F102+標準科目対応!F103 | H29: =標準科目対応!F109 | I29: =G29-H29 | J29: =IF(ABS(I29)<=$K$29,"一致","不一致") | K29: 3
A30: 製造原価の流れ | B30: 当期製品製造原価 | C30: =標準科目対応!E109+標準科目対応!E110-標準科目対応!E111 | D30: =標準科目対応!E112 | E30: =C30-D30 | F30: =IF(ABS(E30)<=$K$30,"一致","不一致") | G30: =標準科目対応!F109+標準科目対応!F110-標準科目対応!F111 | H30: =標準科目対応!F112 | I30: =G30-H30 | J30: =IF(ABS(I30)<=$K$30,"一致","不一致") | K30: 3
A31: 製造原価の流れ | B31: 売上原価（調整表） | C31: =標準科目対応!E113+標準科目対応!E112+標準科目対応!E114-標準科目対応!E115-標準科目対応!E116-標準科目対応!E117 | D31: =標準科目対応!E71 | E31: =C31-D31 | F31: =IF(ABS(E31)<=$K$31,"一致","不一致") | G31: =標準科目対応!F113+標準科目対応!F112+標準科目対応!F114-標準科目対応!F115-標準科目対応!F116-標準科目対応!F117 | H31: =標準科目対応!F71 | I31: =G31-H31 | J31: =IF(ABS(I31)<=$K$31,"一致","不一致") | K31: 6
A32: 主要経営指標との照合 | B32: 売上高 | C32: =標準科目対応!E70 | D32: =標準科目対応!E120 | E32: =C32-D32 | F32: =IF(ABS(E32)<=$K$32,"一致","不一致") | G32: =標準科目対応!F70 | H32: =標準科目対応!F120 | I32: =G32-H32 | J32: =IF(ABS(I32)<=$K$32,"一致","不一致") | K32: 2
A33: 主要経営指標との照合 | B33: 当期純利益 | C33: =標準科目対応!E100 | D33: =標準科目対応!E121 | E33: =C33-D33 | F33: =IF(ABS(E33)<=$K$33,"一致","不一致") | G33: =標準科目対応!F100 | H33: =標準科目対応!F121 | I33: =G33-H33 | J33: =IF(ABS(I33)<=$K$33,"一致","不一致") | K33: 2
A34: 主要経営指標との照合 | B34: 純資産額 | C34: =標準科目対応!E68 | D34: =標準科目対応!E122 | E34: =C34-D34 | F34: =IF(ABS(E34)<=$K$34,"一致","不一致") | G34: =標準科目対応!F68 | H34: =標準科目対応!F122 | I34: =G34-H34 | J34: =IF(ABS(I34)<=$K$34,"一致","不一致") | K34: 2
A35: 主要経営指標との照合 | B35: 総資産額 | C35: =標準科目対応!E34 | D35: =標準科目対応!E123 | E35: =C35-D35 | F35: =IF(ABS(E35)<=$K$35,"一致","不一致") | G35: =標準科目対応!F34 | H35: =標準科目対応!F123 | I35: =G35-H35 | J35: =IF(ABS(I35)<=$K$35,"一致","不一致") | K35: 2
A36: 表間の連携 | B36: BS仕掛品（当期末）＝製造原価の期末仕掛品 | C36: （対象外） | D36: （対象外） | E36: （対象外） | F36: （対象外） | G36: =標準科目対応!F6 | H36: =標準科目対応!F111 | I36: =G36-H36 | J36: =IF(ABS(I36)<=$K$36,"一致","不一致") | K36: 2
A37: 表間の連携 | B37: BS商品及び製品（当期末）＝期末製品＋期末商品 | C37: （対象外） | D37: （対象外） | E37: （対象外） | F37: （対象外） | G37: =標準科目対応!F5 | H37: =標準科目対応!F116+標準科目対応!F117 | I37: =G37-H37 | J37: =IF(ABS(I37)<=$K$37,"一致","不一致") | K37: 2
A38: 前期末と当期首 | B38: 期首製品（当期）＝BS商品及び製品（前期末） | C38: （対象外） | D38: （対象外） | E38: （対象外） | F38: （対象外） | G38: =標準科目対応!F113 | H38: =標準科目対応!E5 | I38: =G38-H38 | J38: =IF(ABS(I38)<=$K$38,"一致","不一致") | K38: 2
A39: 前期末と当期首 | B39: 期首仕掛品（当期）＝BS仕掛品（前期末） | C39: （対象外） | D39: （対象外） | E39: （対象外） | F39: （対象外） | G39: =標準科目対応!F110 | H39: =標準科目対応!E6 | I39: =G39-H39 | J39: =IF(ABS(I39)<=$K$39,"一致","不一致") | K39: 2
A40: 前期末と当期首 | B40: 繰越利益剰余金：前期末＋純利益−配当−別途積立＝当期末 | C40: （対象外） | D40: （対象外） | E40: （対象外） | F40: （対象外） | G40: =標準科目対応!E63+標準科目対応!F100-標準科目対応!F118-標準科目対応!F119 | H40: =標準科目対応!F63 | I40: =G40-H40 | J40: =IF(ABS(I40)<=$K$40,"一致","不一致") | K40: 2
A41: 前期末と当期首 | B41: 別途積立金：前期末＋積立＝当期末 | C41: （対象外） | D41: （対象外） | E41: （対象外） | F41: （対象外） | G41: =標準科目対応!E62+標準科目対応!F119 | H41: =標準科目対応!F62 | I41: =G41-H41 | J41: =IF(ABS(I41)<=$K$41,"一致","不一致") | K41: 2
A43: 総合判定 | B43: =IF(COUNTIF(F4:F41,"不一致")+COUNTIF(J4:J41,"不一致")=0,"全項目一致：次工程へ進める","不一致あり：論争に進まず停止")
A44: 不一致件数 | B44: =COUNTIF(F4:F41,"不一致")+COUNTIF(J4:J41,"不一致")
A45: 端数差の件数 | B45: =COUNTIFS(E4:E41,"<>0",F4:F41,"一致")+COUNTIFS(I4:I41,"<>0",J4:J41,"一致") | C45: 許容範囲内で差が出た件数（切捨て端数による）

Sheet 欠落と扱い
A1: 標準科目 | B1: 原資料での状況 | C1: システムの扱い | D1: 論争での意味
A2: 支払手形 | B2: 該当なし | C2: 0として扱う（該当なしと明示）
A3: 短期借入金 | B3: 該当なし | C3: 0として扱う
A4: 短期貸付金 | B4: 該当なし | C4: 0として扱う
A5: 役員借入金 | B5: 該当なし | C5: 0として扱う | D5: 中小企業では社長個人との混在を示す重要科目
A6: 未収入金・仮払金 | B6: 流動資産『その他』212,878に埋没 | C6: 埋没：データ請求（中小企業なら勘定科目内訳明細書で判明） | D6: 仮払金の滞留は資金の私的流用の兆候になりうる
A7: 保険積立金 | B7: 投資その他『その他』198,610に埋没の可能性 | C7: 埋没：データ請求
A8: 外注加工費 | B8: 製造経費の主な内訳に記載なし | C8: 未確認：ゼロか少額かを請求で確認 | D8: 生産の外部依存度の手がかり
A9: 材料費の内訳（原料米・副材料・包装資材） | B9: 材料費10,453,980の一括表示 | C9: 埋没：データ請求 | D9: 原料米高騰の影響を分離する決め手
A10: 販管費の細目（役員報酬・給料手当・荷造運賃・広告宣伝費・販売促進費・交際費ほか） | B10: 販売費／一般管理費の二区分のみ。連結注記は発送配達費・給料及び手当・賞与引当金繰入額・退職給付費用の4費目 | C10: 未確認：単体注記（p.98以降）を追加で読み取る。なお欠ける費目はデータ請求 | D10: 4Pの販売促進・流通を論じる材料。広告宣伝費と販売促進費が最大の欠落
A11: 労務費の内訳（正社員・臨時・外国人材等） | B11: 労務費4,156,690の一括表示 | C11: 埋没：データ請求
A12: 月別売上 | B12: 有価証券報告書にはなし | C12: 中小企業なら法人事業概況説明書で取得 | D12: 季節変動（年末商戦など）の把握
A13: 得意先別売上 | B13: 連結ベースで主要4社の販売実績あり（p.23） | C13: 上場企業では別情報として取り込み可。中小企業では売掛金の内訳明細が手がかり | D13: 取引先依存度
